{
  "url": "https://www.law.cornell.edu/regulations/new-york/11-NYCRR-153.2",
  "title": "N.Y. Comp. Codes R. & Regs. Tit. 11 ยง 153.2 - Scope",
  "content": "N.Y. Comp. Codes R. & Regs. Tit. 11 ยง 153.2 - Scope\n\nState Regulations\n(a) Property/casualty or liability insurance may be issued or renewed in this State on a group or quasi-group basis only in compliance with this Part. (b) This Part sets forth standards, requirements and procedures governing: (1)\ngroup policies and certificates under section\n3435\nof the Insurance Law; (2)\ngroup policies and certificates in connection with a Federal purchasing group; and\n(3)\nquasi-group policies, through a mass merchandising, safety group or similar program, in connection with State law or a Federal purchasing group. Notes\nN.Y. Comp. Codes R. & Regs. Tit. 11\nยง\n153.2\n\nState regulations are updated quarterly; we currently have two versions available. Below is a\ncomparison between our most recent version and the prior quarterly release. More comparison features will be added as we have more versions to compare. No prior version found.",
  "url_type": "regulation",
  "source_index": 698
}