{
  "url": "https://www.law.cornell.edu/regulations/new-york/2-NYCRR-204.4",
  "title": "N.Y. Comp. Codes R. & Regs. Tit. 2 § 204.4 - Submission of documents and information after the issuance of debt",
  "content": "N.Y. Comp. Codes R. & Regs. Tit. 2 § 204.4 - Submission of documents and information after the issuance of debt\n\nState Regulations\n\nWithin 15 days after the date of issuance, the issuer of debt\nshall furnish to the State Comptroller the following information: (a) a copy of the official statement for the\ndebt issuance in electronic document form; (b) a schedule of sources and uses of\nproceeds associated with the debt that clearly sets forth: i. any market premium or market\ndiscount; ii. the amount of debt\nproceeds to be used to pay issuance costs excluding underwriters' discount and\n\nState bond issuance charges; iii. the amount of proceeds to be used to pay State bond issuance charges; iv. the amount of proceeds to be\nused to pay the underwriters' discount; v. the amount of proceeds to be deposited to\nthe project proceeds account; vi. the amount of proceeds to be deposited to a reserve fund that could be used to\npay debt service; and\nvii. the\namount of proceeds to be deposited to an account that will be used to make debt\nservice payments; (c) a\nschedule of future debt service payments associated with the debt, in\nelectronic format, including: (1)\nfuture\nprincipal payments by payment date; (2)\nfuture interest expected to be paid by\npayment date at rates in effect on the date of issuance; (3)\nfuture swap agreement receipts expected\nto be received by anticipated receipt date based upon rates in effect on the\ndate of issuance; (4)\nfuture swap\nagreement payments expected to be paid by payment date based upon rates in\neffect on the date of issuance; and\n(5)\nan estimate of any future fees or\nexpenses expected to be incurred in relation to the debt issuance. (d) additionally, for refunded\ndebt, a schedule of future cash flows associated with the debt, in electronic\nformat, including: (1)\nthe source and amount\nof funds (other than proceeds of the refunding debt issue) to be used in the\nrefunding; (2)\nthe par amount of\nbonds refunded, by payment date; (3)\nthe refunded debt service, by payment\ndate; (4)\nthe amount of the deposit\nto the escrow agent for payment of the refunded debt; (5)\nthe refunding debt service, by payment\ndate; (6)\nthe annual gross cash\nflow savings or dis-savings as the difference between the refunding and\nrefunded debt service; and\n(7)\nthe\npresent value savings of the cash flow savings discounted at the effective\ninterest rate and adjusted by deducting any funds used in the refunding that\nwere not obtained from proceeds of the refunding debt issue. Notes\nN.Y. Comp. Codes R. & Regs. Tit. 2\n§\n204.4\n\nAmended\n\nNew\n\nYork State Register May 21, 2025/Volume XLVII, Issue 20, eff. 5/21/2025\n\nState regulations are updated quarterly; we currently have two versions available. Below is a\ncomparison between our most recent version and the prior quarterly release. More comparison features will be added as we have more versions to compare. Within 15 days after the\ndate of issuance, the issuer of\ndebt\nshall furnish to the State Comptroller the following information: (a) a copy of the official statement for the\ndebt\nissuance in electronic document form; (b) a schedule of sources and uses of proceeds associated with the\ndebt\nthat clearly sets forth: (1)\nany\nmarket premium\nor\nmarket discount; (2)\nthe amount of\ndebt\nproceeds to be used to pay\nissuance costs\nexcluding underwriters' discount and State bond issuance fees; (3)\nthe amount of proceeds to be used to pay State bond issuance fees; (4)\nthe amount of proceeds to be used to pay the underwriters' discount; (5)\nthe amount of proceeds to be deposited to the\nproject proceeds account; (6)\nthe amount of proceeds to be deposited to a reserve fund that could be used to pay\ndebt\nservice; and\n(7)\nthe amount of proceeds to be deposited to an account that will be used to make\ndebt\nservice payments; (c) a schedule of future\ndebt\nservice payments associated with the\ndebt, in electronic format, including: (1)\nfuture principal payments by payment date; (2)\nfuture interest expected to be paid by payment date at rates in effect on the\ndate of issuance; (3)\nfuture\nswap agreement\nreceipts expected to be received by anticipated receipt date based upon rates in effect on the\ndate of issuance; (4)\nfuture\nswap agreement\npayments expected to be paid by payment date based upon rates in effect on the\ndate of issuance; and\n(5)\nan estimate of any future fees or expenses expected to be incurred in relation to the\ndebt\nissuance. (d) additionally, for refunded\ndebt, a schedule of future cash flows associated with the\ndebt, in electronic format, including: (1)\nthe source and amount of funds (other than proceeds of the refunding\ndebt\nissue) to be used in the refunding; (2)\nthe\npar amount\nof bonds refunded, by payment date; (3)\nthe refunded\ndebt\nservice, by payment date; (4)\nthe amount of the deposit to the escrow agent for payment of the refunded\ndebt; (5)\nthe refunding\ndebt\nservice, by payment date; (6)\nthe annual gross cash flow savings or dis-savings as the difference between the refunding and refunded\ndebt\nservice; and\n(7)\nthe present value savings of the cash flow savings discounted at the\neffective interest rate\nand adjusted by deducting any funds used in the refunding that were not obtained from proceeds of the refunding\ndebt\nissue. Notes\nN.Y. Comp. Codes R. & Regs. Tit. 2\n§\n204.4",
  "url_type": "regulation",
  "source_index": 10465
}