{
  "url": "https://www.law.cornell.edu/regulations/new-york/title-7/chapter-XII/subchapter-B/part-1926",
  "title": "N.Y. Comp. Codes R. & Regs. tit. 7, ch. XII, subch. B, pt. 1926 - MEMORANDUM OF AGREEMENT AND DAY REPORTING RULES",
  "content": "N.Y. Comp. Codes R. & Regs. tit. 7, ch. XII, subch. B, pt. 1926 - MEMORANDUM OF AGREEMENT AND DAY REPORTING RULES\nState Regulations\n§ 1926.1 - In general\n§ 1926.2 - Memorandum of agreement (moa)\n§ 1926.3 - Day reporting rules\n\nNotes\nN.Y. Comp. Codes R. & Regs. tit. 7, ch. XII, subch. B, pt. 1926\n\nStatutory authority: Correction Law, §§73, 112\n\nState regulations are updated quarterly; we currently have two versions available. Below is a\ncomparison between our most recent version and the prior quarterly release. More comparison features will be added as we have more versions to compare. No prior version found.",
  "url_type": "title",
  "source_index": 10933
}