{
  "url": "https://www.law.cornell.edu/regulations/new-york/3-NYCRR-419.11",
  "title": "N.Y. Comp. Codes R. & Regs. Tit. 3 ยง 419.11 - Oversight of third-party providers",
  "content": "N.Y. Comp. Codes R. & Regs. Tit. 3 ยง 419.11 - Oversight of third-party providers\n\nState Regulations\nA servicer shall adopt and maintain policies and procedures\nto oversee and manage third-party providers, including: (a) A servicer shall perform appropriate due\ndiligence of third-party providers' qualifications, expertise, capacity, reputation, complaints, information systems, document custody practices, quality assurance plans, financial viability, and compliance with licensing\nrequirements and applicable rules and regulations. (b) A servicer shall require third-party\nproviders to comply with a servicer's applicable policies and procedures and\napplicable New York and Federal laws and rules. (c) A servicer utilizing third-party\nproviders shall remain responsible for all actions taken by the third-party\nproviders. (d) A servicer shall\nclearly and conspicuously disclose to borrowers if it utilizes a third-party\nprovider and shall clearly and conspicuously disclose to borrowers that the\nservicer remains responsible for all actions taken by third-party\nproviders. (e) A servicer shall\nconduct periodic reviews, not less than annually, of each third-party provider\nthe servicer retains. The review shall be conducted by servicer employees who\nare separate and independent of employees who prepare foreclosure or bankruptcy\naffidavits, sworn documents, declarations, or other foreclosure or bankruptcy\ndocuments. The review shall include: (1)\na\nreview of a sample of the foreclosure and bankruptcy documents prepared by the\nthird-party provider for compliance with applicable New York and Federal laws\nand rules and the accuracy of the facts contained in such documents; (2)\na review of the fees and costs assessed\nby the third-party provider to provide that only fees and costs that are\nlawful, reasonable, and actually incurred are charged to borrowers and that no\nportion of any fees or charges incurred by any third-party provider for\ntechnology usage, connectivity, or electronic invoice submission is charged as\na cost to the borrower; (3)\na\nreview of the third-party provider's processes to provide for compliance with\nthe servicer's policies and procedures; (4)\na review of the security of original loan\ndocuments maintained by the third-party provider; (5)\na review of customer complaints\nconcerning third-party providers; and\n(6)\na requirement that the third-party\nprovider disclose to the servicer: (i) any\ninstance where any party requests the imposition of sanctions or that\nprofessional disciplinary action be taken against the third-party provider for\nmisconduct related to the services the third-party provider provides to the\nservicer; and\n(ii)\nany imposition\nof sanctions or professional disciplinary action taken against the third-party\nprovider for misconduct related to the services the third-party provider\nprovides to the servicer. (f) A servicer shall ensure that all\nthird-party providers have appropriate and reliable contact information for\nservicer employees who possess information relevant to the services provided by\nthe third-party provider. A servicer shall ensure that foreclosure and\nbankruptcy counsel have an appropriate servicer contact to assist in legal\nproceedings and to facilitate loss mitigation questions on behalf of a\nborrower. (g) A servicer shall take\nappropriate remedial steps if a servicer identifies any problems through the\nreview required by subdivision (e) of this section or otherwise, including\nterminating its relationship with a third-party provider. (h) A servicer shall develop and implement\npolicies and procedures detailing how the servicer will oversee and communicate\nwith counsel and those with the authority to fully dispose of the case\nconcerning foreclosure proceedings. Such policies shall, at a minimum: (1)\ndetail how notice will be provided to\nforeclosure attorneys and trustees regarding a borrower's status for\nconsideration of a loss mitigation option and whether the borrower is being\nevaluated for, or is currently in, a trial or permanent modification; (2)\nensure that its foreclosure attorneys\ncomply with the requirements of New York Civil Practice Law and Rules section\n3408 with regard to mandatory settlement conferences in residential foreclosure\nactions; and\n(3)\na servicer shall\ndevelop and implement policies and procedures to ensure that its foreclosure\nattorneys comply with all applicable legal requirements including all relevant\n\nAdministrative Orders of the Chief Administrative Judge of the Courts of New\n\nYork. Notes\nN.Y. Comp. Codes R. & Regs. Tit. 3\nยง\n419.11\n\nAmended\n\nNew\n\nYork State Register December 18, 2019/Volume XLI, Issue 51, eff. 12/18/2019\n\nState regulations are updated quarterly; we currently have two versions available. Below is a\ncomparison between our most recent version and the prior quarterly release. More comparison features will be added as we have more versions to compare. No prior version found.",
  "url_type": "regulation",
  "source_index": 11604
}