{
  "url": "https://www.law.cornell.edu/regulations/new-york/1-NYCRR-203.6",
  "title": "N.Y. Comp. Codes R. & Regs. Tit. 1 ยง 203.6 - Duties and responsibilities of the advisory board",
  "content": "N.Y. Comp. Codes R. & Regs. Tit. 1 ยง 203.6 - Duties and responsibilities of the advisory board\n\nState Regulations\n\nIt shall be the duty of the advisory board to advise and\nassist the commissioner in all matters pertaining to the operation of this\nprogram, subject only to such limitations as may be prescribed in section\n294\nof the Agriculture and Markets Law. Such duties may specifically include any or\nall of the following: (a) the\nrecommendation to the commissioner of administrative rules and regulations\nrelating to the program; (b) recommending to the commissioner such amendments to the program as seem\nadvisable; (c) the preparation and\nsubmission to the commissioner of the estimated budget required for the proper\noperation of the program; (d) recommending to the commissioner methods for assessing members of the industry\nand methods for collecting the necessary funds; (e) assisting the commissioner in the\ncollection and assembling of information and data necessary to the proper\nadministration of the order; and\n(f) the performance of such other duties in\nconnection with the program as the commissioner shall designate. Notes\nN.Y. Comp. Codes R. & Regs. Tit. 1\nยง\n203.6\n\nState regulations are updated quarterly; we currently have two versions available. Below is a\ncomparison between our most recent version and the prior quarterly release. More comparison features will be added as we have more versions to compare. No prior version found.",
  "url_type": "regulation",
  "source_index": 17844
}