{
  "url": "https://www.law.cornell.edu/regulations/new-york/21-NYCRR-1808.17",
  "title": "N.Y. Comp. Codes R. & Regs. Tit. 21 ยง 1808.17 - Enforcement of penalties, abatement or remedial orders",
  "content": "N.Y. Comp. Codes R. & Regs. Tit. 21 ยง 1808.17 - Enforcement of penalties, abatement or remedial orders\n\nState Regulations\n\nAny penalty imposed or abatement or remedial action ordered\nby the commission or the executive director shall be paid or completed within\nsuch time period as shall be specified in the civil penalty assessment or\norder. The executive director and commission counsel are authorized to take\nsuch additional action as may be necessary to assure compliance with sections\n1808.10\n-1808.19 of this Part. If\na proceeding before a court becomes necessary, the penalty amount determined in\naccordance with section\n1808.15\n(f) of\nthis Part shall constitute the penalty amount recommended by the commission to\nbe fixed by the court pursuant to section 15.17 of the\ncompact. Notes\nN.Y. Comp. Codes R. & Regs. Tit. 21\nยง\n1808.17\n\nState regulations are updated quarterly; we currently have two versions available. Below is a\ncomparison between our most recent version and the prior quarterly release. More comparison features will be added as we have more versions to compare. No prior version found.",
  "url_type": "regulation",
  "source_index": 21308
}