{
  "url": "https://www.law.cornell.edu/regulations/new-york/20-NYCRR-471.7",
  "title": "N.Y. Comp. Codes R. & Regs. Tit. 20 ยง 471.7 - Motor vehicles transporting household goods",
  "content": "N.Y. Comp. Codes R. & Regs. Tit. 20 ยง 471.7 - Motor vehicles transporting household goods\n\nState Regulations\n\nTax Law, ยง 504, subd. 5\nA motor vehicle is exempt if it is used exclusively in\nthe transportation of household goods, as defined by the Commissioner of\n\nTransportation of the State of New York or the Interstate Commerce Commission, by a carrier under the authority of the Commissioner of Transportation of this\n\nState or the Interstate Commerce Commission. Notes\nN.Y. Comp. Codes R. & Regs. Tit. 20\nยง\n471.7\n\nState regulations are updated quarterly; we currently have two versions available. Below is a\ncomparison between our most recent version and the prior quarterly release. More comparison features will be added as we have more versions to compare. No prior version found.",
  "url_type": "regulation",
  "source_index": 26345
}