{
  "url": "https://www.law.cornell.edu/regulations/new-york/19-NYCRR-203.23",
  "title": "N.Y. Comp. Codes R. & Regs. Tit. 19 ยง 203.23 - Crematory operator course examination requirement and record retention",
  "content": "N.Y. Comp. Codes R. & Regs. Tit. 19 ยง 203.23 - Crematory operator course examination requirement and record retention\n\nState Regulations\n(a) All approved\norganizations shall retain the attendance records, the final examinations and a\nlist of crematory employees who successfully complete each certification course\nfor a period of five years after completion of each course. All such documents\nshall during normal business hours be available for inspection by authorized\nrepresentatives of the Division of Cemeteries. (b) All examination required for\ncertification shall be in the form of a written take home examination and shall\nbe returned to the educational provider within two weeks after\ndistribution. Notes\nN.Y. Comp. Codes\nR. & Regs. Tit. 19\nยง\n203.23\n\nRenumbered from 204.9\n\nNew\n\nYork State Register August 7, 2024/Volume XLVI, Issue 32, eff. 8/7/2024\n\nState regulations are updated quarterly; we currently have two versions available. Below is a\ncomparison between our most recent version and the prior quarterly release. More comparison features will be added as we have more versions to compare. No prior version found.",
  "url_type": "regulation",
  "source_index": 26532
}