{
  "url": "https://www.law.cornell.edu/regulations/new-york/9-NYCRR-8201.7",
  "title": "N.Y. Comp. Codes R. & Regs. Tit. 9 ยง 8201.7 - Requests for public access to records",
  "content": "N.Y. Comp. Codes R. & Regs. Tit. 9 ยง 8201.7 - Requests for public access to records\n\nState Regulations\n(a) A request for records shall be in\nwriting; however, the requirement of a written request may be waived by the\nrecords access officer for the convenience of the council upon a showing of\nhardship by the person seeking access. (b) A response shall be given regarding any\nrequest reasonably describing the record or records sought within five business\ndays of receipt of the request. (c) A request shall reasonably describe the record or records sought. Whenever\npossible, a person requesting records should supply information regarding\ndates, file designations or other information that may help to describe the\nrecords sought. (d) If the records\naccess officer does not provide or deny access to the record sought within five\nbusiness days of receipt of a request, he or she shall furnish a written\nacknowledgment of receipt of the request and a statement of the approximate\ndate when the request will be granted or denied. If access to records is\nneither granted nor denied within 10 business days after the date of\nacknowledgment of receipt of a request, the request may be construed as a\ndenial of access that may be appealed. Notes\nN.Y. Comp. Codes\nR. & Regs. Tit. 9\nยง\n8201.7\n\nState regulations are updated quarterly; we currently have two versions available. Below is a\ncomparison between our most recent version and the prior quarterly release. More comparison features will be added as we have more versions to compare. No prior version found.",
  "url_type": "regulation",
  "source_index": 27952
}