{
  "url": "https://www.law.cornell.edu/regulations/new-york/6-NYCRR-645-4.15",
  "title": "N.Y. Comp. Codes R. & Regs. Tit. 6 §§ 645-4.15 - Waiver of rules",
  "content": "N.Y. Comp. Codes R. & Regs. Tit. 6 §§ 645-4.15 - Waiver of rules\n\nState Regulations\n\nAny of the foregoing rules may be waived by stipulation\nof the parties with consent of the commission or, if a hearing officer has been\nappointed, with consent of the hearing officer. Notes\nN.Y. Comp. Codes R. & Regs. Tit. 6\n§§\n645-4.15\n\nState regulations are updated quarterly; we currently have two versions available. Below is a\ncomparison between our most recent version and the prior quarterly release. More comparison features will be added as we have more versions to compare. No prior version found.",
  "url_type": "regulation",
  "source_index": 31560
}