{
  "url": "https://www.law.cornell.edu/regulations/new-york/22-NYCRR-D-ch-IV-app-Paternity-Forms-form-5-4",
  "title": "N.Y. Comp. Codes R. & Regs. tit. 22, subtit. D, ch. IV, subch. A, Paternity Forms (Family Court Act Article 5), form 5-4 - Notice of motion-challenge to testing directive",
  "content": "N.Y. Comp. Codes R. & Regs. tit. 22, subtit. D, ch. IV, subch. A, Paternity Forms (Family Court Act Article 5), form 5-4 - Notice of motion-challenge to testing directive\n\nState Regulations\n\nImage\n\nImage\n\nNotes\nN.Y. Comp. Codes R. & Regs. tit. 22, subtit. D, ch. IV, subch. A, Paternity Forms\n(Family Court Act Article 5), form\n5-4\n\nState regulations are updated quarterly; we currently have two versions available. Below is a\ncomparison between our most recent version and the prior quarterly release. More comparison features will be added as we have more versions to compare. No prior version found.",
  "url_type": "regulation",
  "source_index": 35628
}