{
  "url": "https://www.law.cornell.edu/regulations/new-york/8-NYCRR-72.8",
  "title": "N.Y. Comp. Codes R. & Regs. Tit. 8 ยง 72.8 - License by endorsement of certain psychologists",
  "content": "N.Y. Comp. Codes R. & Regs. Tit. 8 ยง 72.8 - License by endorsement of certain psychologists\n\nState Regulations\n\nAn applicant seeking endorsement of a license in psychology\nissued by another state, country or territory shall present evidence of: (a) age, the applicant shall be at least 21\nyears of age at the time of application; (b) licensure by another jurisdiction with\nstandards equivalent to New York State as determined by the\ndepartment; (c) completion and\naward of a doctoral degree in psychology, that at the time of completion\nqualified the applicant for licensure as a psychologist in the other\njurisdiction; (d) completion of\nsupervised experience in psychology that qualified the applicant for initial\nlicensure in the other jurisdiction; (e) passage of an examination acceptable to\nthe department for the practice of psychology; (f) at least five years of experience in\npsychology satisfactory to the State Board for Psychology, within the 10 years\nimmediately preceding the application for licensure by endorsement in New York\n\nState; (g) completion of coursework\nin the identification and reporting of suspected child abuse and neglect or the\nexemption from such coursework, as specified in 6507(3) of the Education\n\nLaw; (h) good moral character as\ndetermined by the department; and\n(i) acceptable licensure and discipline\nstatus in each jurisdiction in which the applicant holds a professional\nlicense. Notes\nN.Y. Comp. Codes R. & Regs. Tit. 8\nยง\n72.8\n\nAdopted\n\nNew\n\nYork State Register March 30, 2022/Volume XLIV, Issue 13, eff. 3/30/2022\n\nState regulations are updated quarterly; we currently have two versions available. Below is a\ncomparison between our most recent version and the prior quarterly release. More comparison features will be added as we have more versions to compare. No prior version found.",
  "url_type": "regulation",
  "source_index": 36895
}