{
  "url": "https://www.law.cornell.edu/regulations/new-york/6-NYCRR-651.52",
  "title": "N.Y. Comp. Codes R. & Regs. Tit. 6 ยง 651.52 - Advance estimates",
  "content": "N.Y. Comp. Codes R. & Regs. Tit. 6 ยง 651.52 - Advance estimates\n\nState Regulations\nA municipality shall file with the commissioner, not\nlater than May 1st of each year, an estimate or future total eligible costs for\nthe fiscal year specified by the commissioner. Failure to submit such advance\nestimate may disqualify the municipality for State assistance for said\nmunicipal fiscal year. Notes\nN.Y. Comp. Codes R. & Regs. Tit. 6\nยง\n651.52\n\nState regulations are updated quarterly; we currently have two versions available. Below is a\ncomparison between our most recent version and the prior quarterly release. More comparison features will be added as we have more versions to compare. No prior version found.",
  "url_type": "regulation",
  "source_index": 37225
}