{
  "url": "https://www.law.cornell.edu/regulations/new-york/title-7/chapter-VIII/part-700",
  "title": "N.Y. Comp. Codes R. & Regs. tit. 7, ch. VIII, pt. 700 - Appeal Of Correctional Industries Prices",
  "content": "N.Y. Comp. Codes R. & Regs. tit. 7, ch. VIII, pt. 700 - Appeal Of Correctional Industries Prices\n\nState Regulations\n§ 700.1 - Scope of regulation\n§ 700.2 - Who may appeal; timeliness\n§ 700.3 - Statutory time limit for filing an appeal\n§ 700.4 - Manner of bringing appeal\n§ 700.5 - Deinitions\n§ 700.6 - Office of the price review board\n§ 700.7 - Chairman\n§ 700.8 - Powers and duties of the price review board\n§ 700.9 - Appearance before the board\n§ 700.10 - Hearings\n§ 700.11 - Authorized dispositions\n§ 700.12 - Change of address\n§ 700.13 - Withdrawal of appeal\n§ 700.14 - Construction\n\nNotes\nN.Y. Comp. Codes R. & Regs. tit. 7, ch. VIII, pt. 700\n\nStatutory authority: Correction Law, §112\n\nState regulations are updated quarterly; we currently have two versions available. Below is a\ncomparison between our most recent version and the prior quarterly release. More comparison features will be added as we have more versions to compare. No prior version found.",
  "url_type": "title",
  "source_index": 42594
}