{
  "url": "https://www.law.cornell.edu/regulations/new-york/9-NYCRR-6218.10",
  "title": "N.Y. Comp. Codes R. & Regs. Tit. 9 ยง 6218.10 - Adjournments",
  "content": "N.Y. Comp. Codes R. & Regs. Tit. 9 ยง 6218.10 - Adjournments\n\nState Regulations\n(a) To the extent practicable requests for adjournment must be made by written\naffidavit addressed to the hearing officer, and must be received at the office\nof the State Board no later than three business days prior to the scheduled\ndate of hearing. The affidavit must contain sufficient details to explain the\nreason for the request so as to enable the hearing officer to rule\nthereon. (b) The first request of\nany party to adjourn an adjudicatory hearing will be granted by the hearing\nofficer for good cause shown, and any subsequent adjournment requests of such\nparty will be granted by the hearing officer if necessary to avoid real\nprejudice to the requesting party. Notes\nN.Y. Comp. Codes\nR. & Regs. Tit. 9\nยง\n6218.10\n\nAdopted\n\nNew\n\nYork State Register November 10, 2015/Volume XXXVII, Issue 45, eff. 11/10/2015\n\nState regulations are updated quarterly; we currently have two versions available. Below is a\ncomparison between our most recent version and the prior quarterly release. More comparison features will be added as we have more versions to compare. No prior version found.",
  "url_type": "regulation",
  "source_index": 43905
}