{
  "url": "https://www.law.cornell.edu/regulations/new-york/title-17/chapter-VI/subchapter-E/article-2",
  "title": "Article 2 - Service",
  "content": "Article 2 - Service\n\nState Regulations\n\nPart 810 - Issuance Of Bills Of Lading And Freight Bills By Common Carriers (Repealed)\n\nPart 811 - Repealed\n\nPart 812 - Repealed\n\nPart 813 - Repealed\n\nPart 814 - Transportation of Household Goods by Common Carriers (ยง 814.0 to 814.9)\n\nState regulations are updated quarterly; we currently have two versions available. Below is a\ncomparison between our most recent version and the prior quarterly release. More comparison features will be added as we have more versions to compare. No prior version found.",
  "url_type": "title",
  "source_index": 45339
}