{
  "url": "https://www.law.cornell.edu/regulations/new-york/23-NYCRR-2.2",
  "title": "N.Y. Comp. Codes R. & Regs. Tit. 23 ยง 2.2 - Hearing officer",
  "content": "N.Y. Comp. Codes R. & Regs. Tit. 23 ยง 2.2 - Hearing officer\n\nState Regulations\n(a) A hearing in\nan adjudicatory proceeding shall be conducted by a hearing officer chosen from\namong the following persons: (1)\nthe\n\nSuperintendent of Financial Services; (2)\nany Deputy Superintendent; or\n(3)\nany designated salaried employee of the\n\nDepartment authorized by the Superintendent for such purpose. (b) A hearing officer shall have\nthe powers set forth in State Administrative Procedures Act section 304. (c) No person who shall have\npreviously dealt in a substantial way with the substance of the matter that is\nthe subject of the adjudicatory proceeding, or who has an existing or potential\nconflict of interest, shall act as the hearing officer in such proceeding. (d) A hearing officer shall be\nbound by the Department's code of ethics and the code of ethics as set forth in\n\nPublic Officers Law section 74. (e) An application to recuse a hearing\nofficer may be made by any party on the hearing record. The hearing officer\nshall rule on such application in accordance with the above codes of ethics. (f) In the event of a hearing\nofficer's death, resignation, removal, recusal, termination of employment, disability, or other inability or failure to otherwise conclude a hearing or\nmake a timely written report after the completion of the hearing, another duly\ndesignated hearing officer may be substituted to continue the hearing on the\nexisting record or to render a written report on the completed record. Notes\nN.Y. Comp. Codes R. & Regs. Tit. 23\nยง\n2.2\n\nAdopted\n\nNew\n\nYork State Register March 25, 2020/Volume XLII, Issue 12, eff. 3/25/2020\n\nState regulations are updated quarterly; we currently have two versions available. Below is a\ncomparison between our most recent version and the prior quarterly release. More comparison features will be added as we have more versions to compare. No prior version found.",
  "url_type": "regulation",
  "source_index": 46175
}