{
  "url": "https://www.law.cornell.edu/regulations/new-york/title-9/subtitle-T/chapter-I/subchapter-A/article-3",
  "title": "Article 3 - NEW YORK-BRED THOROUGHBREDS",
  "content": "Article 3 - NEW YORK-BRED THOROUGHBREDS\nState Regulations\n\nPart 4080 - New York State Thoroughbred Breeding And Development Fund (ยง 4080.1 to 4080.5)\n\nPart 4081 - New York-bred Eligibility (ยง 4081.1 to 4081.13)\n\nPart 4082 - Distributions (ยง 4082.1 to 4082.4)\n\nState regulations are updated quarterly; we currently have two versions available. Below is a\ncomparison between our most recent version and the prior quarterly release. More comparison features will be added as we have more versions to compare. No prior version found.",
  "url_type": "title",
  "source_index": 48512
}