{
  "url": "https://www.law.cornell.edu/regulations/new-york/8-NYCRR-574.4",
  "title": "N.Y. Comp. Codes R. & Regs. Tit. 8 ยง 574.4 - Parking",
  "content": "N.Y. Comp. Codes R. & Regs. Tit. 8 ยง 574.4 - Parking\n\nState Regulations\n(a) No person shall\npark a vehicle in any area except those areas specifically designated as\nvehicle parking lots or spaces. (Service areas are not parking\nareas.)\n(b) Students may park\nvehicles only in those areas specifically designated as student parking\nareas. (c) No person may park a\nvehicle within a parking area other than in the space designated for the\nparking or standing of a vehicle as indicated by posted signs, pavement\nmarkings, or painted lines restricting or limiting such parking. (d) No person shall fail to observe and obey\nany duly posted sign regulating traffic entering upon, within or exiting from\nany parking area. (e) Parking fees\nas approved by the campus president, or designee, shall be charged for motor\nvehicles parked within designated lots, consistent with applicable collective\nbargaining agreements and in accordance with guidelines established by the\ncampus president or designee. Such guidelines shall provide that the\ndetermination of the amount of the fee be substantially based on an analysis of\nthe costs attributable to the operation and maintenance of the parking\nfacilities owned and operated by the College of Technology at Delhi. Notes\nN.Y. Comp. Codes R. & Regs. Tit. 8\nยง\n574.4\n\nState regulations are updated quarterly; we currently have two versions available. Below is a\ncomparison between our most recent version and the prior quarterly release. More comparison features will be added as we have more versions to compare. No prior version found.",
  "url_type": "regulation",
  "source_index": 48774
}