{
  "url": "https://www.law.cornell.edu/regulations/new-york/title-1/chapter-VII/part-350",
  "title": "N.Y. Comp. Codes R. & Regs. tit. 1, ch. VII, pt. 350 - Standards For Conduct Of Fairs",
  "content": "N.Y. Comp. Codes R. & Regs. tit. 1, ch. VII, pt. 350 - Standards For Conduct Of Fairs\n\nState Regulations\n§ 350.1 - Fair sponsor; definition\n§ 350.2 - No fee for 4-h, f.f.a., junior fair or school department exhibits\n§ 350.3 - Prompt, full payment of premiums\n§ 350.4 - No premium for unworthy exhibit\n§ 350.5 - Premium amount to attract well-balanced exhibits\n§ 350.6 - No exhibits by judges in departments they oversee\n§ 350.7 - Exhibits to be plainly labeled\n§ 350.8 - Reexhibition in domestic department\n§ 350.9 - Ownership of exhibits entered in fairs and shows\n§ 350.10 - Rejection or refusal of an exhibit\n§ 350.11 - Compliance with and enforcement of livestock health requirements\n§ 350.12 - Repealed\n§ 350.13 to 350.17 - Repealed\n§ 350.18 - Repealed\n\nNotes\nN.Y. Comp. Codes\nR. & Regs. tit. 1, ch. VII, pt. 350\n\nStatutory authority: Agriculture and Markets Law, §§3, 16, 17, 18, 287\n\nState regulations are updated quarterly; we currently have two versions available. Below is a\ncomparison between our most recent version and the prior quarterly release. More comparison features will be added as we have more versions to compare. No prior version found.",
  "url_type": "title",
  "source_index": 49811
}